youtube2zim/__about__.py
youtube2zim/__init__.py
youtube2zim/__main__.py
youtube2zim/constants.py
youtube2zim/entrypoint.py
youtube2zim/processing.py
youtube2zim/schemas.py
youtube2zim/scraper.py
youtube2zim/utils.py
youtube2zim/youtube.py
youtube2zim/playlists/__init__.py
youtube2zim/playlists/__main__.py
youtube2zim/playlists/entrypoint.py
youtube2zim/playlists/scraper.py
youtube2zim-3.5.0.dist-info/METADATA
youtube2zim-3.5.0.dist-info/WHEEL
youtube2zim-3.5.0.dist-info/entry_points.txt
youtube2zim-3.5.0.dist-info/RECORD
