Metadata-Version: 2.4
Name: youtube2zim
Version: 3.5.0
Summary: Make ZIM file from a Youtube channel, user or playlist(s)
Project-URL: Donate, https://www.kiwix.org/en/support-us/
Project-URL: Homepage, https://www.kiwix.org
Author-email: openZIM <dev@openzim.org>
License: GPL-3.0-or-later
Keywords: offline,openzim,youtube,zim
Classifier: License :: OSI Approved :: GNU General Public License v3 or later (GPLv3+)
Classifier: Programming Language :: Python :: 3
Classifier: Programming Language :: Python :: 3.14
Requires-Python: <3.15,>=3.14
Requires-Dist: jinja2==3.1.6
Requires-Dist: kiwixstorage==0.10.1
Requires-Dist: pif==0.8.2
Requires-Dist: pydantic==2.12.4
Requires-Dist: pyhumps==3.8.0
Requires-Dist: python-dateutil==2.9.0.post0
Requires-Dist: python-slugify==8.0.4
Requires-Dist: requests==2.32.5
Requires-Dist: schedule==1.2.2
Requires-Dist: yt-dlp[curl-cffi,default]
Requires-Dist: zimscraperlib==5.3.0
Provides-Extra: check
Requires-Dist: pyright==1.1.407; extra == 'check'
Provides-Extra: dev
Requires-Dist: black==25.11.0; extra == 'dev'
Requires-Dist: coverage==7.11.3; extra == 'dev'
Requires-Dist: debugpy==1.8.17; extra == 'dev'
Requires-Dist: humanfriendly==10.0; extra == 'dev'
Requires-Dist: invoke==2.2.1; extra == 'dev'
Requires-Dist: pre-commit==4.4.0; extra == 'dev'
Requires-Dist: pyright==1.1.407; extra == 'dev'
Requires-Dist: pytest==9.0.1; extra == 'dev'
Requires-Dist: ruff==0.14.5; extra == 'dev'
Provides-Extra: lint
Requires-Dist: black==25.11.0; extra == 'lint'
Requires-Dist: ruff==0.14.5; extra == 'lint'
Provides-Extra: scripts
Requires-Dist: invoke==2.2.1; extra == 'scripts'
Provides-Extra: test
Requires-Dist: coverage==7.11.3; extra == 'test'
Requires-Dist: pytest==9.0.1; extra == 'test'
